msgpack-stubs/__init__.pyi
msgpack-stubs/_cmsgpack.pyi
msgpack-stubs/exceptions.pyi
msgpack-stubs/ext.pyi
msgpack-stubs/fallback.pyi
msgpack_types-0.5.0.dist-info/LICENSE
msgpack_types-0.5.0.dist-info/METADATA
msgpack_types-0.5.0.dist-info/WHEEL
msgpack_types-0.5.0.dist-info/RECORD
